{
  "standard": "OWASP ASVS",
  "version": "5.0.0",
  "source": "https://github.com/OWASP/ASVS/releases/tag/v5.0.0_release",
  "requirementSetSha256": "ab3851f4fd75c5ac6b666ccd2fce4c1ff0bbb464da480d9730b341c4cccc4925",
  "authInvariants": [
    {
      "id": "AUTH-INV-001",
      "asvs": ["v5.0.0-2.2.1", "v5.0.0-15.3.1", "v5.0.0-15.3.5"],
      "commands": ["pnpm test:auth-adapter", "pnpm check:auth-logical-ids"],
      "evidence": [
        "test/unit/convex-auth-adapter-invariants.test.ts",
        "playground/convex/auth-adapter-invariants.test.ts",
        "scripts/check-auth-logical-ids.mjs"
      ]
    },
    {
      "id": "AUTH-INV-002",
      "asvs": ["v5.0.0-2.3.3", "v5.0.0-2.3.4"],
      "commands": ["pnpm test:auth-concurrency", "pnpm test:auth-adapter"],
      "evidence": [
        "playground/convex/authConcurrency.ts",
        "playground/convex/auth-adapter-invariants.test.ts",
        "scripts/run-auth-concurrency.mjs"
      ]
    },
    {
      "id": "AUTH-INV-002A",
      "asvs": ["v5.0.0-2.3.3", "v5.0.0-15.3.3"],
      "commands": ["pnpm test:auth-adapter", "pnpm test:auth-mutations"],
      "evidence": [
        "test/unit/convex-auth-adapter-invariants.test.ts",
        "src/runtime/convex-auth/component/adapter.ts",
        "test/mutations/adapter-security-mutants.test.ts"
      ]
    },
    {
      "id": "AUTH-INV-003",
      "asvs": ["v5.0.0-2.2.1", "v5.0.0-15.3.5"],
      "commands": ["pnpm test:auth-adapter"],
      "evidence": [
        "test/unit/convex-auth-adapter-invariants.test.ts",
        "src/runtime/convex-auth/adapter/create-adapter.ts"
      ]
    },
    {
      "id": "AUTH-INV-004",
      "asvs": ["v5.0.0-2.2.1", "v5.0.0-15.3.3"],
      "commands": ["pnpm test:auth-adapter"],
      "evidence": [
        "test/unit/convex-auth-adapter-invariants.test.ts",
        "src/runtime/convex-auth/adapter/create-adapter.ts"
      ]
    },
    {
      "id": "AUTH-INV-005",
      "asvs": ["v5.0.0-2.3.3", "v5.0.0-2.3.4"],
      "commands": ["pnpm test:auth-concurrency", "pnpm test:auth-mutations"],
      "evidence": [
        "src/runtime/convex-auth/component/adapter.ts",
        "playground/convex/authConcurrency.ts",
        "test/mutations/adapter-security-mutants.test.ts"
      ]
    },
    {
      "id": "AUTH-INV-006",
      "asvs": ["v5.0.0-2.3.3", "v5.0.0-2.3.4"],
      "commands": ["pnpm test:auth-concurrency", "pnpm test:auth-mutations"],
      "evidence": [
        "src/runtime/convex-auth/component/adapter.ts",
        "playground/convex/authConcurrency.ts",
        "test/mutations/adapter-security-mutants.test.ts"
      ]
    },
    {
      "id": "AUTH-INV-007",
      "asvs": ["v5.0.0-2.2.3", "v5.0.0-15.2.2"],
      "commands": ["pnpm test:auth-adapter", "pnpm check:auth-schema"],
      "evidence": [
        "src/runtime/convex-auth/adapter/generate-schema.ts",
        "test/unit/convex-auth-adapter-invariants.test.ts",
        "scripts/check-auth-schema.mjs"
      ]
    },
    {
      "id": "AUTH-INV-007A",
      "asvs": ["v5.0.0-2.2.3", "v5.0.0-15.3.5"],
      "commands": ["pnpm test:auth-adapter"],
      "evidence": [
        "src/runtime/convex-auth/adapter/query.ts",
        "test/unit/convex-auth-adapter-invariants.test.ts"
      ]
    },
    {
      "id": "AUTH-INV-008",
      "asvs": ["v5.0.0-8.2.1", "v5.0.0-16.5.3"],
      "commands": ["pnpm test:auth-adapter", "pnpm test:auth-mutations"],
      "evidence": [
        "src/runtime/convex-auth/context.ts",
        "test/unit/convex-auth-adapter-invariants.test.ts",
        "test/mutations/adapter-security-mutants.test.ts"
      ]
    },
    {
      "id": "AUTH-INV-009",
      "asvs": ["v5.0.0-3.4.2", "v5.0.0-13.2.4"],
      "commands": ["pnpm test:oauth", "pnpm test:auth-fuzz"],
      "evidence": [
        "src/runtime/shared/auth-origin.ts",
        "test/unit/auth-origin.test.ts",
        "test/security/better-auth-static-origin.test.ts"
      ]
    },
    {
      "id": "AUTH-INV-009A",
      "asvs": ["v5.0.0-2.4.1", "v5.0.0-4.1.3", "v5.0.0-15.3.4"],
      "commands": ["pnpm test:auth-concurrency", "pnpm test:auth-fuzz"],
      "evidence": [
        "src/runtime/shared/client-ip.ts",
        "scripts/run-oauth-transport-quota.mjs",
        "test/unit/oauth-transport-quota.test.ts",
        "test/unit/auth-proxy-client-ip.test.ts"
      ]
    },
    {
      "id": "AUTH-INV-010",
      "asvs": ["v5.0.0-3.5.1", "v5.0.0-10.1.1"],
      "commands": ["pnpm test:e2e:full", "pnpm check:boundaries"],
      "evidence": [
        "src/runtime/server/api/auth/[...].ts",
        "test/e2e/auth-proxy-raw-wire-hardening.e2e.test.ts",
        "test/unit/convex-auth-boundaries.test.ts"
      ]
    },
    {
      "id": "AUTH-INV-011",
      "asvs": ["v5.0.0-6.3.4", "v5.0.0-7.2.1", "v5.0.0-7.4.1"],
      "commands": ["pnpm test:auth-mfa", "pnpm test:e2e:full"],
      "evidence": [
        "src/runtime/convex-auth/internal-session.ts",
        "test/security/convex-auth-internal-session.test.ts",
        "test/e2e/extended/auth-two-factor.e2e.test.ts"
      ]
    },
    {
      "id": "AUTH-INV-012",
      "asvs": ["v5.0.0-10.1.1", "v5.0.0-14.3.3"],
      "commands": ["pnpm test:oauth", "pnpm test:e2e:full"],
      "evidence": [
        "src/runtime/convex-auth/plugin.ts",
        "test/e2e/auth-proxy-raw-wire-hardening.e2e.test.ts",
        "test/e2e/extended/auth-two-factor.e2e.test.ts"
      ]
    },
    {
      "id": "AUTH-INV-013",
      "asvs": ["v5.0.0-9.2.2", "v5.0.0-10.3.1"],
      "commands": ["pnpm test:oauth"],
      "evidence": [
        "src/runtime/convex-auth/oauth-resource.ts",
        "test/security/convex-auth-oauth-resource.test.ts",
        "test/security/convex-auth-internal-session.test.ts"
      ]
    },
    {
      "id": "AUTH-INV-014",
      "asvs": [
        "v5.0.0-9.1.1",
        "v5.0.0-9.1.2",
        "v5.0.0-9.1.3",
        "v5.0.0-9.2.1",
        "v5.0.0-9.2.2",
        "v5.0.0-9.2.3"
      ],
      "commands": ["pnpm test:oauth"],
      "evidence": [
        "src/runtime/convex-auth/oauth-resource.ts",
        "test/security/convex-auth-oauth-resource.test.ts",
        "test/security/convex-auth-oauth-provider-integration.test.ts"
      ]
    },
    {
      "id": "AUTH-INV-015",
      "asvs": ["v5.0.0-8.2.3", "v5.0.0-15.3.1"],
      "commands": ["pnpm test:oauth", "pnpm test:auth-mfa"],
      "evidence": [
        "src/runtime/convex-auth/plugin.ts",
        "test/security/convex-auth-oauth-security.test.ts",
        "test/e2e/extended/auth-two-factor.e2e.test.ts"
      ]
    },
    {
      "id": "AUTH-INV-016",
      "asvs": ["v5.0.0-9.1.3", "v5.0.0-11.1.1", "v5.0.0-11.2.2"],
      "commands": ["pnpm test:oauth", "pnpm test:auth-concurrency"],
      "evidence": [
        "src/runtime/convex-auth/jwks-rotation.ts",
        "test/security/convex-auth-jwks-rotation.test.ts",
        "scripts/run-auth-concurrency.mjs"
      ]
    },
    {
      "id": "AUTH-INV-017",
      "asvs": ["v5.0.0-13.3.2", "v5.0.0-15.3.1", "v5.0.0-16.5.1"],
      "commands": ["pnpm test:oauth"],
      "evidence": [
        "src/runtime/convex-auth/jwks-rotation.ts",
        "test/security/convex-auth-jwks-rotation.test.ts"
      ]
    },
    {
      "id": "AUTH-INV-018",
      "asvs": [
        "v5.0.0-2.3.1",
        "v5.0.0-2.3.3",
        "v5.0.0-10.4.1",
        "v5.0.0-10.4.2",
        "v5.0.0-10.4.3",
        "v5.0.0-10.4.6",
        "v5.0.0-10.4.10"
      ],
      "commands": ["pnpm test:oauth", "pnpm test:auth-concurrency"],
      "evidence": [
        "src/runtime/convex-auth/plugin.ts",
        "scripts/run-oauth-code-concurrency.mjs",
        "test/security/convex-auth-oauth-provider-integration.test.ts",
        "test/security/convex-auth-oauth-security.test.ts",
        "test/unit/oauth-code-concurrency.test.ts"
      ]
    },
    {
      "id": "AUTH-INV-019",
      "asvs": ["v5.0.0-9.2.3", "v5.0.0-9.2.4", "v5.0.0-10.3.1"],
      "commands": ["pnpm test:oauth"],
      "evidence": [
        "src/runtime/convex-auth/oauth-resource.ts",
        "test/security/convex-auth-oauth-resource.test.ts",
        "test/security/convex-auth-oauth-provider-integration.test.ts"
      ]
    },
    {
      "id": "AUTH-INV-020",
      "asvs": ["v5.0.0-8.3.1", "v5.0.0-10.3.2"],
      "commands": ["pnpm test:oauth", "pnpm test:mcp-auth"],
      "evidence": [
        "test/mcp/mcp-live-authorization.test.ts",
        "starters/mcp-oauth-agent/convex/mcpTools.ts"
      ]
    },
    {
      "id": "AUTH-INV-020A",
      "asvs": ["v5.0.0-8.2.1", "v5.0.0-8.2.2", "v5.0.0-8.3.1", "v5.0.0-10.1.1"],
      "commands": ["pnpm test:mcp-auth", "pnpm check:boundaries"],
      "evidence": [
        "src/runtime/server/mcp/proxy.ts",
        "test/mcp/mcp-boundaries.test.ts",
        "starters/mcp-oauth-agent/convex/mcp.ts"
      ]
    },
    {
      "id": "AUTH-INV-021",
      "asvs": ["v5.0.0-10.4.4", "v5.0.0-15.2.3"],
      "commands": ["pnpm test:oauth"],
      "evidence": [
        "src/runtime/convex-auth/oauth-security.ts",
        "test/security/convex-auth-oauth-provider-integration.test.ts"
      ]
    },
    {
      "id": "AUTH-INV-022",
      "asvs": [
        "v5.0.0-13.3.1",
        "v5.0.0-13.3.2",
        "v5.0.0-14.1.1",
        "v5.0.0-14.1.2",
        "v5.0.0-14.2.4",
        "v5.0.0-16.2.5"
      ],
      "commands": [
        "pnpm test",
        "pnpm test:auth-sentinels",
        "pnpm test:auth-export-sentinels",
        "pnpm test:auth-fuzz",
        "pnpm check:package-exports"
      ],
      "evidence": [
        "SECURITY.md",
        "scripts/auth-secret-sentinels.mjs",
        "scripts/run-auth-export-sentinels.mjs",
        "scripts/run-auth-sentinels.mjs",
        "test/security/auth-secret-sentinels.test.ts",
        "test/security/proxy-regressions.test.ts",
        "test/security/session-observer-regressions.test.ts",
        "test/unit/auth-export-sentinels.test.ts",
        "test/unit/convex-auth-id-token-encryption.test.ts",
        "test/unit/devtools-auth-proxy-registry.test.ts",
        "test/unit/server-auth-snapshot.test.ts",
        "test/unit/token-fetcher.test.ts"
      ]
    },
    {
      "id": "AUTH-INV-023",
      "asvs": ["v5.0.0-2.2.1", "v5.0.0-2.2.2", "v5.0.0-15.3.5", "v5.0.0-16.5.3"],
      "commands": ["pnpm check:auth-schema", "pnpm test:auth-adapter"],
      "evidence": [
        "scripts/generate-auth-schema.mjs",
        "src/runtime/convex-auth/adapter/generate-schema.ts",
        "scripts/check-auth-schema.mjs"
      ]
    },
    {
      "id": "AUTH-INV-024",
      "asvs": ["v5.0.0-6.3.4", "v5.0.0-15.2.3"],
      "commands": ["pnpm check:boundaries", "pnpm check:better-auth-local-component"],
      "evidence": [
        "src/runtime/convex-auth/adapter/create-adapter.ts",
        "test/unit/convex-auth-boundaries.test.ts",
        "test/fixtures/better-auth-local-component/convex/betterAuth/adapter.ts"
      ]
    },
    {
      "id": "AUTH-INV-025",
      "asvs": ["v5.0.0-15.1.2", "v5.0.0-15.2.3"],
      "commands": ["pnpm release:verify", "pnpm check:package-exports"],
      "evidence": [
        "scripts/release.mjs",
        "scripts/verify-release.mjs",
        "test/unit/release-artifact-evidence.test.ts"
      ]
    },
    {
      "id": "AUTH-INV-026",
      "asvs": ["v5.0.0-7.4.1", "v5.0.0-8.3.1", "v5.0.0-9.2.1"],
      "commands": ["pnpm test:oauth", "pnpm test:mcp-auth"],
      "evidence": [
        "test/mcp/mcp-live-authorization.test.ts",
        "src/runtime/convex-auth/oauth-resource.ts",
        "test/security/convex-auth-oauth-provider-integration.test.ts"
      ]
    },
    {
      "id": "AUTH-INV-027",
      "asvs": ["v5.0.0-13.3.1", "v5.0.0-13.4.2", "v5.0.0-16.5.3"],
      "commands": ["pnpm check:auth-schema", "pnpm test:oauth"],
      "evidence": [
        "scripts/generate-auth-schema.mjs",
        "src/runtime/convex-auth/create-auth-component.ts",
        "test/unit/shipped-auth-factories.test.ts"
      ]
    },
    {
      "id": "AUTH-INV-028",
      "asvs": ["v5.0.0-6.3.4", "v5.0.0-15.2.3", "v5.0.0-16.5.3"],
      "commands": ["pnpm check:auth-schema", "pnpm check:boundaries"],
      "evidence": [
        "scripts/check-auth-schema.mjs",
        "test/unit/convex-auth-boundaries.test.ts",
        "test/fixtures/better-auth-local-component/convex/convex.config.ts"
      ]
    },
    {
      "id": "AUTH-INV-029",
      "asvs": ["v5.0.0-8.2.1", "v5.0.0-8.2.2", "v5.0.0-8.3.1", "v5.0.0-16.5.3"],
      "commands": ["pnpm test:oauth", "pnpm test:auth-mutations"],
      "evidence": [
        "src/runtime/convex-auth/oauth-security.ts",
        "test/security/convex-auth-oauth-security.test.ts",
        "test/security/convex-auth-oauth-provider-integration.test.ts"
      ]
    }
  ],
  "requirements": [
    {
      "id": "v5.0.0-1.1.1",
      "level": 2,
      "chapter": "Encoding and Sanitization",
      "responsibility": "consumer",
      "status": "external",
      "evidence": "Consumer application control; outside the library boundary."
    },
    {
      "id": "v5.0.0-1.1.2",
      "level": 2,
      "chapter": "Encoding and Sanitization",
      "responsibility": "consumer",
      "status": "external",
      "evidence": "Consumer application control; outside the library boundary."
    },
    {
      "id": "v5.0.0-1.2.1",
      "level": 1,
      "chapter": "Encoding and Sanitization",
      "responsibility": "consumer",
      "status": "external",
      "evidence": "Consumer application control; outside the library boundary."
    },
    {
      "id": "v5.0.0-1.2.2",
      "level": 1,
      "chapter": "Encoding and Sanitization",
      "responsibility": "library",
      "status": "verified",
      "evidence": "test/security/proxy-property-regressions.test.ts"
    },
    {
      "id": "v5.0.0-1.2.3",
      "level": 1,
      "chapter": "Encoding and Sanitization",
      "responsibility": "consumer",
      "status": "external",
      "evidence": "Consumer application control; outside the library boundary."
    },
    {
      "id": "v5.0.0-1.2.4",
      "level": 1,
      "chapter": "Encoding and Sanitization",
      "responsibility": "consumer",
      "status": "external",
      "evidence": "Consumer application control; outside the library boundary."
    },
    {
      "id": "v5.0.0-1.2.5",
      "level": 1,
      "chapter": "Encoding and Sanitization",
      "responsibility": "consumer",
      "status": "external",
      "evidence": "Consumer application control; outside the library boundary."
    },
    {
      "id": "v5.0.0-1.2.6",
      "level": 2,
      "chapter": "Encoding and Sanitization",
      "responsibility": "consumer",
      "status": "external",
      "evidence": "Consumer application control; outside the library boundary."
    },
    {
      "id": "v5.0.0-1.2.7",
      "level": 2,
      "chapter": "Encoding and Sanitization",
      "responsibility": "consumer",
      "status": "external",
      "evidence": "Consumer application control; outside the library boundary."
    },
    {
      "id": "v5.0.0-1.2.8",
      "level": 2,
      "chapter": "Encoding and Sanitization",
      "responsibility": "consumer",
      "status": "external",
      "evidence": "Consumer application control; outside the library boundary."
    },
    {
      "id": "v5.0.0-1.2.9",
      "level": 2,
      "chapter": "Encoding and Sanitization",
      "responsibility": "consumer",
      "status": "external",
      "evidence": "Consumer application control; outside the library boundary."
    },
    {
      "id": "v5.0.0-1.3.1",
      "level": 1,
      "chapter": "Encoding and Sanitization",
      "responsibility": "consumer",
      "status": "external",
      "evidence": "Consumer application control; outside the library boundary."
    },
    {
      "id": "v5.0.0-1.3.2",
      "level": 1,
      "chapter": "Encoding and Sanitization",
      "responsibility": "consumer",
      "status": "external",
      "evidence": "Consumer application control; outside the library boundary."
    },
    {
      "id": "v5.0.0-1.3.3",
      "level": 2,
      "chapter": "Encoding and Sanitization",
      "responsibility": "consumer",
      "status": "external",
      "evidence": "Consumer application control; outside the library boundary."
    },
    {
      "id": "v5.0.0-1.3.4",
      "level": 2,
      "chapter": "Encoding and Sanitization",
      "responsibility": "consumer",
      "status": "external",
      "evidence": "Consumer application control; outside the library boundary."
    },
    {
      "id": "v5.0.0-1.3.5",
      "level": 2,
      "chapter": "Encoding and Sanitization",
      "responsibility": "consumer",
      "status": "external",
      "evidence": "Consumer application control; outside the library boundary."
    },
    {
      "id": "v5.0.0-1.3.6",
      "level": 2,
      "chapter": "Encoding and Sanitization",
      "responsibility": "library",
      "status": "verified",
      "evidence": "src/runtime/utils/site-url.ts"
    },
    {
      "id": "v5.0.0-1.3.7",
      "level": 2,
      "chapter": "Encoding and Sanitization",
      "responsibility": "consumer",
      "status": "external",
      "evidence": "Consumer application control; outside the library boundary."
    },
    {
      "id": "v5.0.0-1.3.8",
      "level": 2,
      "chapter": "Encoding and Sanitization",
      "responsibility": "consumer",
      "status": "external",
      "evidence": "Consumer application control; outside the library boundary."
    },
    {
      "id": "v5.0.0-1.3.9",
      "level": 2,
      "chapter": "Encoding and Sanitization",
      "responsibility": "consumer",
      "status": "external",
      "evidence": "Consumer application control; outside the library boundary."
    },
    {
      "id": "v5.0.0-1.3.10",
      "level": 2,
      "chapter": "Encoding and Sanitization",
      "responsibility": "consumer",
      "status": "external",
      "evidence": "Consumer application control; outside the library boundary."
    },
    {
      "id": "v5.0.0-1.3.11",
      "level": 2,
      "chapter": "Encoding and Sanitization",
      "responsibility": "consumer",
      "status": "external",
      "evidence": "Consumer application control; outside the library boundary."
    },
    {
      "id": "v5.0.0-1.4.1",
      "level": 2,
      "chapter": "Encoding and Sanitization",
      "responsibility": "consumer",
      "status": "external",
      "evidence": "Consumer application control; outside the library boundary."
    },
    {
      "id": "v5.0.0-1.4.2",
      "level": 2,
      "chapter": "Encoding and Sanitization",
      "responsibility": "consumer",
      "status": "external",
      "evidence": "Consumer application control; outside the library boundary."
    },
    {
      "id": "v5.0.0-1.4.3",
      "level": 2,
      "chapter": "Encoding and Sanitization",
      "responsibility": "consumer",
      "status": "external",
      "evidence": "Consumer application control; outside the library boundary."
    },
    {
      "id": "v5.0.0-1.5.1",
      "level": 1,
      "chapter": "Encoding and Sanitization",
      "responsibility": "consumer",
      "status": "external",
      "evidence": "Consumer application control; outside the library boundary."
    },
    {
      "id": "v5.0.0-1.5.2",
      "level": 2,
      "chapter": "Encoding and Sanitization",
      "responsibility": "consumer",
      "status": "external",
      "evidence": "Consumer application control; outside the library boundary."
    },
    {
      "id": "v5.0.0-2.1.1",
      "level": 1,
      "chapter": "Validation and Business Logic",
      "responsibility": "consumer",
      "status": "external",
      "evidence": "Consumer application control; outside the library boundary."
    },
    {
      "id": "v5.0.0-2.1.2",
      "level": 2,
      "chapter": "Validation and Business Logic",
      "responsibility": "consumer",
      "status": "external",
      "evidence": "Consumer application control; outside the library boundary."
    },
    {
      "id": "v5.0.0-2.1.3",
      "level": 2,
      "chapter": "Validation and Business Logic",
      "responsibility": "consumer",
      "status": "external",
      "evidence": "Consumer application control; outside the library boundary."
    },
    {
      "id": "v5.0.0-2.2.1",
      "level": 1,
      "chapter": "Validation and Business Logic",
      "responsibility": "consumer",
      "status": "external",
      "evidence": "Consumer application control; outside the library boundary."
    },
    {
      "id": "v5.0.0-2.2.2",
      "level": 1,
      "chapter": "Validation and Business Logic",
      "responsibility": "consumer",
      "status": "external",
      "evidence": "Consumer application control; outside the library boundary."
    },
    {
      "id": "v5.0.0-2.2.3",
      "level": 2,
      "chapter": "Validation and Business Logic",
      "responsibility": "consumer",
      "status": "external",
      "evidence": "Consumer application control; outside the library boundary."
    },
    {
      "id": "v5.0.0-2.3.1",
      "level": 1,
      "chapter": "Validation and Business Logic",
      "responsibility": "consumer",
      "status": "external",
      "evidence": "Consumer application control; outside the library boundary."
    },
    {
      "id": "v5.0.0-2.3.2",
      "level": 2,
      "chapter": "Validation and Business Logic",
      "responsibility": "consumer",
      "status": "external",
      "evidence": "Consumer application control; outside the library boundary."
    },
    {
      "id": "v5.0.0-2.3.3",
      "level": 2,
      "chapter": "Validation and Business Logic",
      "responsibility": "consumer",
      "status": "external",
      "evidence": "Consumer application control; outside the library boundary."
    },
    {
      "id": "v5.0.0-2.3.4",
      "level": 2,
      "chapter": "Validation and Business Logic",
      "responsibility": "consumer",
      "status": "external",
      "evidence": "Consumer application control; outside the library boundary."
    },
    {
      "id": "v5.0.0-2.4.1",
      "level": 2,
      "chapter": "Validation and Business Logic",
      "responsibility": "consumer",
      "status": "external",
      "evidence": "Consumer application control; outside the library boundary."
    },
    {
      "id": "v5.0.0-3.2.1",
      "level": 1,
      "chapter": "Web Frontend Security",
      "responsibility": "deployment",
      "status": "external",
      "evidence": "Deployment control; operator verification required."
    },
    {
      "id": "v5.0.0-3.2.2",
      "level": 1,
      "chapter": "Web Frontend Security",
      "responsibility": "deployment",
      "status": "external",
      "evidence": "Deployment control; operator verification required."
    },
    {
      "id": "v5.0.0-3.3.1",
      "level": 1,
      "chapter": "Web Frontend Security",
      "responsibility": "deployment",
      "status": "external",
      "evidence": "Deployment control; operator verification required."
    },
    {
      "id": "v5.0.0-3.3.2",
      "level": 2,
      "chapter": "Web Frontend Security",
      "responsibility": "deployment",
      "status": "external",
      "evidence": "Deployment control; operator verification required."
    },
    {
      "id": "v5.0.0-3.3.3",
      "level": 2,
      "chapter": "Web Frontend Security",
      "responsibility": "deployment",
      "status": "external",
      "evidence": "Deployment control; operator verification required."
    },
    {
      "id": "v5.0.0-3.3.4",
      "level": 2,
      "chapter": "Web Frontend Security",
      "responsibility": "deployment",
      "status": "external",
      "evidence": "Deployment control; operator verification required."
    },
    {
      "id": "v5.0.0-3.4.1",
      "level": 1,
      "chapter": "Web Frontend Security",
      "responsibility": "deployment",
      "status": "external",
      "evidence": "Deployment control; operator verification required."
    },
    {
      "id": "v5.0.0-3.4.2",
      "level": 1,
      "chapter": "Web Frontend Security",
      "responsibility": "library",
      "status": "verified",
      "evidence": "src/runtime/server/api/auth/security.ts"
    },
    {
      "id": "v5.0.0-3.4.3",
      "level": 2,
      "chapter": "Web Frontend Security",
      "responsibility": "deployment",
      "status": "external",
      "evidence": "Deployment control; operator verification required."
    },
    {
      "id": "v5.0.0-3.4.4",
      "level": 2,
      "chapter": "Web Frontend Security",
      "responsibility": "deployment",
      "status": "external",
      "evidence": "Deployment control; operator verification required."
    },
    {
      "id": "v5.0.0-3.4.5",
      "level": 2,
      "chapter": "Web Frontend Security",
      "responsibility": "deployment",
      "status": "external",
      "evidence": "Deployment control; operator verification required."
    },
    {
      "id": "v5.0.0-3.4.6",
      "level": 2,
      "chapter": "Web Frontend Security",
      "responsibility": "deployment",
      "status": "external",
      "evidence": "Deployment control; operator verification required."
    },
    {
      "id": "v5.0.0-3.5.1",
      "level": 1,
      "chapter": "Web Frontend Security",
      "responsibility": "library",
      "status": "verified",
      "evidence": "test/security/proxy-regressions.test.ts"
    },
    {
      "id": "v5.0.0-3.5.2",
      "level": 1,
      "chapter": "Web Frontend Security",
      "responsibility": "library",
      "status": "verified",
      "evidence": "test/security/proxy-regressions.test.ts"
    },
    {
      "id": "v5.0.0-3.5.3",
      "level": 1,
      "chapter": "Web Frontend Security",
      "responsibility": "deployment",
      "status": "external",
      "evidence": "Deployment control; operator verification required."
    },
    {
      "id": "v5.0.0-3.5.4",
      "level": 2,
      "chapter": "Web Frontend Security",
      "responsibility": "deployment",
      "status": "external",
      "evidence": "Deployment control; operator verification required."
    },
    {
      "id": "v5.0.0-3.5.5",
      "level": 2,
      "chapter": "Web Frontend Security",
      "responsibility": "deployment",
      "status": "external",
      "evidence": "Deployment control; operator verification required."
    },
    {
      "id": "v5.0.0-3.7.1",
      "level": 2,
      "chapter": "Web Frontend Security",
      "responsibility": "deployment",
      "status": "external",
      "evidence": "Deployment control; operator verification required."
    },
    {
      "id": "v5.0.0-3.7.2",
      "level": 2,
      "chapter": "Web Frontend Security",
      "responsibility": "deployment",
      "status": "external",
      "evidence": "Deployment control; operator verification required."
    },
    {
      "id": "v5.0.0-4.1.1",
      "level": 1,
      "chapter": "API and Web Service",
      "responsibility": "consumer",
      "status": "external",
      "evidence": "Consumer application control; outside the library boundary."
    },
    {
      "id": "v5.0.0-4.1.2",
      "level": 2,
      "chapter": "API and Web Service",
      "responsibility": "consumer",
      "status": "external",
      "evidence": "Consumer application control; outside the library boundary."
    },
    {
      "id": "v5.0.0-4.1.3",
      "level": 2,
      "chapter": "API and Web Service",
      "responsibility": "library",
      "status": "verified",
      "evidence": "src/runtime/server/api/auth/headers.ts"
    },
    {
      "id": "v5.0.0-4.2.1",
      "level": 2,
      "chapter": "API and Web Service",
      "responsibility": "library",
      "status": "verified",
      "evidence": "src/runtime/server/api/auth/headers.ts"
    },
    {
      "id": "v5.0.0-4.3.1",
      "level": 2,
      "chapter": "API and Web Service",
      "responsibility": "consumer",
      "status": "external",
      "evidence": "Consumer application control; outside the library boundary."
    },
    {
      "id": "v5.0.0-4.3.2",
      "level": 2,
      "chapter": "API and Web Service",
      "responsibility": "consumer",
      "status": "external",
      "evidence": "Consumer application control; outside the library boundary."
    },
    {
      "id": "v5.0.0-4.4.1",
      "level": 1,
      "chapter": "API and Web Service",
      "responsibility": "consumer",
      "status": "external",
      "evidence": "Consumer application control; outside the library boundary."
    },
    {
      "id": "v5.0.0-4.4.2",
      "level": 2,
      "chapter": "API and Web Service",
      "responsibility": "consumer",
      "status": "external",
      "evidence": "Consumer application control; outside the library boundary."
    },
    {
      "id": "v5.0.0-4.4.3",
      "level": 2,
      "chapter": "API and Web Service",
      "responsibility": "consumer",
      "status": "external",
      "evidence": "Consumer application control; outside the library boundary."
    },
    {
      "id": "v5.0.0-4.4.4",
      "level": 2,
      "chapter": "API and Web Service",
      "responsibility": "consumer",
      "status": "external",
      "evidence": "Consumer application control; outside the library boundary."
    },
    {
      "id": "v5.0.0-5.1.1",
      "level": 2,
      "chapter": "File Handling",
      "responsibility": "consumer",
      "status": "external",
      "evidence": "Consumer application control; outside the library boundary."
    },
    {
      "id": "v5.0.0-5.2.1",
      "level": 1,
      "chapter": "File Handling",
      "responsibility": "consumer",
      "status": "external",
      "evidence": "Consumer application control; outside the library boundary."
    },
    {
      "id": "v5.0.0-5.2.2",
      "level": 1,
      "chapter": "File Handling",
      "responsibility": "consumer",
      "status": "external",
      "evidence": "Consumer application control; outside the library boundary."
    },
    {
      "id": "v5.0.0-5.2.3",
      "level": 2,
      "chapter": "File Handling",
      "responsibility": "consumer",
      "status": "external",
      "evidence": "Consumer application control; outside the library boundary."
    },
    {
      "id": "v5.0.0-5.3.1",
      "level": 1,
      "chapter": "File Handling",
      "responsibility": "consumer",
      "status": "external",
      "evidence": "Consumer application control; outside the library boundary."
    },
    {
      "id": "v5.0.0-5.3.2",
      "level": 1,
      "chapter": "File Handling",
      "responsibility": "consumer",
      "status": "external",
      "evidence": "Consumer application control; outside the library boundary."
    },
    {
      "id": "v5.0.0-5.4.1",
      "level": 2,
      "chapter": "File Handling",
      "responsibility": "consumer",
      "status": "external",
      "evidence": "Consumer application control; outside the library boundary."
    },
    {
      "id": "v5.0.0-5.4.2",
      "level": 2,
      "chapter": "File Handling",
      "responsibility": "consumer",
      "status": "external",
      "evidence": "Consumer application control; outside the library boundary."
    },
    {
      "id": "v5.0.0-5.4.3",
      "level": 2,
      "chapter": "File Handling",
      "responsibility": "consumer",
      "status": "external",
      "evidence": "Consumer application control; outside the library boundary."
    },
    {
      "id": "v5.0.0-6.1.1",
      "level": 1,
      "chapter": "Authentication",
      "responsibility": "upstream",
      "status": "external",
      "evidence": "Pinned Better Auth or Convex control; integration and provider verification required."
    },
    {
      "id": "v5.0.0-6.1.2",
      "level": 2,
      "chapter": "Authentication",
      "responsibility": "upstream",
      "status": "external",
      "evidence": "Pinned Better Auth or Convex control; integration and provider verification required."
    },
    {
      "id": "v5.0.0-6.1.3",
      "level": 2,
      "chapter": "Authentication",
      "responsibility": "upstream",
      "status": "external",
      "evidence": "Pinned Better Auth or Convex control; integration and provider verification required."
    },
    {
      "id": "v5.0.0-6.2.1",
      "level": 1,
      "chapter": "Authentication",
      "responsibility": "upstream",
      "status": "external",
      "evidence": "Pinned Better Auth or Convex control; integration and provider verification required."
    },
    {
      "id": "v5.0.0-6.2.2",
      "level": 1,
      "chapter": "Authentication",
      "responsibility": "upstream",
      "status": "external",
      "evidence": "Pinned Better Auth or Convex control; integration and provider verification required."
    },
    {
      "id": "v5.0.0-6.2.3",
      "level": 1,
      "chapter": "Authentication",
      "responsibility": "upstream",
      "status": "external",
      "evidence": "Pinned Better Auth or Convex control; integration and provider verification required."
    },
    {
      "id": "v5.0.0-6.2.4",
      "level": 1,
      "chapter": "Authentication",
      "responsibility": "upstream",
      "status": "external",
      "evidence": "Pinned Better Auth or Convex control; integration and provider verification required."
    },
    {
      "id": "v5.0.0-6.2.5",
      "level": 1,
      "chapter": "Authentication",
      "responsibility": "upstream",
      "status": "external",
      "evidence": "Pinned Better Auth or Convex control; integration and provider verification required."
    },
    {
      "id": "v5.0.0-6.2.6",
      "level": 1,
      "chapter": "Authentication",
      "responsibility": "upstream",
      "status": "external",
      "evidence": "Pinned Better Auth or Convex control; integration and provider verification required."
    },
    {
      "id": "v5.0.0-6.2.7",
      "level": 1,
      "chapter": "Authentication",
      "responsibility": "upstream",
      "status": "external",
      "evidence": "Pinned Better Auth or Convex control; integration and provider verification required."
    },
    {
      "id": "v5.0.0-6.2.8",
      "level": 1,
      "chapter": "Authentication",
      "responsibility": "upstream",
      "status": "external",
      "evidence": "Pinned Better Auth or Convex control; integration and provider verification required."
    },
    {
      "id": "v5.0.0-6.2.9",
      "level": 2,
      "chapter": "Authentication",
      "responsibility": "upstream",
      "status": "external",
      "evidence": "Pinned Better Auth or Convex control; integration and provider verification required."
    },
    {
      "id": "v5.0.0-6.2.10",
      "level": 2,
      "chapter": "Authentication",
      "responsibility": "upstream",
      "status": "external",
      "evidence": "Pinned Better Auth or Convex control; integration and provider verification required."
    },
    {
      "id": "v5.0.0-6.2.11",
      "level": 2,
      "chapter": "Authentication",
      "responsibility": "upstream",
      "status": "external",
      "evidence": "Pinned Better Auth or Convex control; integration and provider verification required."
    },
    {
      "id": "v5.0.0-6.2.12",
      "level": 2,
      "chapter": "Authentication",
      "responsibility": "upstream",
      "status": "external",
      "evidence": "Pinned Better Auth or Convex control; integration and provider verification required."
    },
    {
      "id": "v5.0.0-6.3.1",
      "level": 1,
      "chapter": "Authentication",
      "responsibility": "upstream",
      "status": "external",
      "evidence": "Pinned Better Auth or Convex control; integration and provider verification required."
    },
    {
      "id": "v5.0.0-6.3.2",
      "level": 1,
      "chapter": "Authentication",
      "responsibility": "upstream",
      "status": "external",
      "evidence": "Pinned Better Auth or Convex control; integration and provider verification required."
    },
    {
      "id": "v5.0.0-6.3.3",
      "level": 2,
      "chapter": "Authentication",
      "responsibility": "upstream",
      "status": "external",
      "evidence": "Pinned Better Auth or Convex control; integration and provider verification required."
    },
    {
      "id": "v5.0.0-6.3.4",
      "level": 2,
      "chapter": "Authentication",
      "responsibility": "upstream",
      "status": "external",
      "evidence": "Pinned Better Auth or Convex control; integration and provider verification required."
    },
    {
      "id": "v5.0.0-6.4.1",
      "level": 1,
      "chapter": "Authentication",
      "responsibility": "upstream",
      "status": "external",
      "evidence": "Pinned Better Auth or Convex control; integration and provider verification required."
    },
    {
      "id": "v5.0.0-6.4.2",
      "level": 1,
      "chapter": "Authentication",
      "responsibility": "upstream",
      "status": "external",
      "evidence": "Pinned Better Auth or Convex control; integration and provider verification required."
    },
    {
      "id": "v5.0.0-6.4.3",
      "level": 2,
      "chapter": "Authentication",
      "responsibility": "upstream",
      "status": "external",
      "evidence": "Pinned Better Auth or Convex control; integration and provider verification required."
    },
    {
      "id": "v5.0.0-6.4.4",
      "level": 2,
      "chapter": "Authentication",
      "responsibility": "upstream",
      "status": "external",
      "evidence": "Pinned Better Auth or Convex control; integration and provider verification required."
    },
    {
      "id": "v5.0.0-6.5.1",
      "level": 2,
      "chapter": "Authentication",
      "responsibility": "upstream",
      "status": "external",
      "evidence": "Pinned Better Auth or Convex control; integration and provider verification required."
    },
    {
      "id": "v5.0.0-6.5.2",
      "level": 2,
      "chapter": "Authentication",
      "responsibility": "upstream",
      "status": "external",
      "evidence": "Pinned Better Auth or Convex control; integration and provider verification required."
    },
    {
      "id": "v5.0.0-6.5.3",
      "level": 2,
      "chapter": "Authentication",
      "responsibility": "upstream",
      "status": "external",
      "evidence": "Pinned Better Auth or Convex control; integration and provider verification required."
    },
    {
      "id": "v5.0.0-6.5.4",
      "level": 2,
      "chapter": "Authentication",
      "responsibility": "upstream",
      "status": "external",
      "evidence": "Pinned Better Auth or Convex control; integration and provider verification required."
    },
    {
      "id": "v5.0.0-6.5.5",
      "level": 2,
      "chapter": "Authentication",
      "responsibility": "upstream",
      "status": "external",
      "evidence": "Pinned Better Auth or Convex control; integration and provider verification required."
    },
    {
      "id": "v5.0.0-6.6.1",
      "level": 2,
      "chapter": "Authentication",
      "responsibility": "upstream",
      "status": "external",
      "evidence": "Pinned Better Auth or Convex control; integration and provider verification required."
    },
    {
      "id": "v5.0.0-6.6.2",
      "level": 2,
      "chapter": "Authentication",
      "responsibility": "upstream",
      "status": "external",
      "evidence": "Pinned Better Auth or Convex control; integration and provider verification required."
    },
    {
      "id": "v5.0.0-6.6.3",
      "level": 2,
      "chapter": "Authentication",
      "responsibility": "upstream",
      "status": "external",
      "evidence": "Pinned Better Auth or Convex control; integration and provider verification required."
    },
    {
      "id": "v5.0.0-6.8.1",
      "level": 2,
      "chapter": "Authentication",
      "responsibility": "upstream",
      "status": "external",
      "evidence": "Pinned Better Auth or Convex control; integration and provider verification required."
    },
    {
      "id": "v5.0.0-6.8.2",
      "level": 2,
      "chapter": "Authentication",
      "responsibility": "upstream",
      "status": "external",
      "evidence": "Pinned Better Auth or Convex control; integration and provider verification required."
    },
    {
      "id": "v5.0.0-6.8.3",
      "level": 2,
      "chapter": "Authentication",
      "responsibility": "upstream",
      "status": "external",
      "evidence": "Pinned Better Auth or Convex control; integration and provider verification required."
    },
    {
      "id": "v5.0.0-6.8.4",
      "level": 2,
      "chapter": "Authentication",
      "responsibility": "upstream",
      "status": "external",
      "evidence": "Pinned Better Auth or Convex control; integration and provider verification required."
    },
    {
      "id": "v5.0.0-7.1.1",
      "level": 2,
      "chapter": "Session Management",
      "responsibility": "upstream",
      "status": "external",
      "evidence": "Pinned Better Auth or Convex control; integration and provider verification required."
    },
    {
      "id": "v5.0.0-7.1.2",
      "level": 2,
      "chapter": "Session Management",
      "responsibility": "upstream",
      "status": "external",
      "evidence": "Pinned Better Auth or Convex control; integration and provider verification required."
    },
    {
      "id": "v5.0.0-7.1.3",
      "level": 2,
      "chapter": "Session Management",
      "responsibility": "upstream",
      "status": "external",
      "evidence": "Pinned Better Auth or Convex control; integration and provider verification required."
    },
    {
      "id": "v5.0.0-7.2.1",
      "level": 1,
      "chapter": "Session Management",
      "responsibility": "upstream",
      "status": "external",
      "evidence": "Pinned Better Auth or Convex control; integration and provider verification required."
    },
    {
      "id": "v5.0.0-7.2.2",
      "level": 1,
      "chapter": "Session Management",
      "responsibility": "upstream",
      "status": "external",
      "evidence": "Pinned Better Auth or Convex control; integration and provider verification required."
    },
    {
      "id": "v5.0.0-7.2.3",
      "level": 1,
      "chapter": "Session Management",
      "responsibility": "upstream",
      "status": "external",
      "evidence": "Pinned Better Auth or Convex control; integration and provider verification required."
    },
    {
      "id": "v5.0.0-7.2.4",
      "level": 1,
      "chapter": "Session Management",
      "responsibility": "upstream",
      "status": "external",
      "evidence": "Pinned Better Auth or Convex control; integration and provider verification required."
    },
    {
      "id": "v5.0.0-7.3.1",
      "level": 2,
      "chapter": "Session Management",
      "responsibility": "upstream",
      "status": "external",
      "evidence": "Pinned Better Auth or Convex control; integration and provider verification required."
    },
    {
      "id": "v5.0.0-7.3.2",
      "level": 2,
      "chapter": "Session Management",
      "responsibility": "upstream",
      "status": "external",
      "evidence": "Pinned Better Auth or Convex control; integration and provider verification required."
    },
    {
      "id": "v5.0.0-7.4.1",
      "level": 1,
      "chapter": "Session Management",
      "responsibility": "upstream",
      "status": "external",
      "evidence": "Pinned Better Auth or Convex control; integration and provider verification required."
    },
    {
      "id": "v5.0.0-7.4.2",
      "level": 1,
      "chapter": "Session Management",
      "responsibility": "upstream",
      "status": "external",
      "evidence": "Pinned Better Auth or Convex control; integration and provider verification required."
    },
    {
      "id": "v5.0.0-7.4.3",
      "level": 2,
      "chapter": "Session Management",
      "responsibility": "upstream",
      "status": "external",
      "evidence": "Pinned Better Auth or Convex control; integration and provider verification required."
    },
    {
      "id": "v5.0.0-7.4.4",
      "level": 2,
      "chapter": "Session Management",
      "responsibility": "upstream",
      "status": "external",
      "evidence": "Pinned Better Auth or Convex control; integration and provider verification required."
    },
    {
      "id": "v5.0.0-7.4.5",
      "level": 2,
      "chapter": "Session Management",
      "responsibility": "upstream",
      "status": "external",
      "evidence": "Pinned Better Auth or Convex control; integration and provider verification required."
    },
    {
      "id": "v5.0.0-7.5.1",
      "level": 2,
      "chapter": "Session Management",
      "responsibility": "upstream",
      "status": "external",
      "evidence": "Pinned Better Auth or Convex control; integration and provider verification required."
    },
    {
      "id": "v5.0.0-7.5.2",
      "level": 2,
      "chapter": "Session Management",
      "responsibility": "upstream",
      "status": "external",
      "evidence": "Pinned Better Auth or Convex control; integration and provider verification required."
    },
    {
      "id": "v5.0.0-7.6.1",
      "level": 2,
      "chapter": "Session Management",
      "responsibility": "upstream",
      "status": "external",
      "evidence": "Pinned Better Auth or Convex control; integration and provider verification required."
    },
    {
      "id": "v5.0.0-7.6.2",
      "level": 2,
      "chapter": "Session Management",
      "responsibility": "upstream",
      "status": "external",
      "evidence": "Pinned Better Auth or Convex control; integration and provider verification required."
    },
    {
      "id": "v5.0.0-8.1.1",
      "level": 1,
      "chapter": "Authorization",
      "responsibility": "consumer",
      "status": "external",
      "evidence": "Consumer application control; outside the library boundary."
    },
    {
      "id": "v5.0.0-8.1.2",
      "level": 2,
      "chapter": "Authorization",
      "responsibility": "consumer",
      "status": "external",
      "evidence": "Consumer application control; outside the library boundary."
    },
    {
      "id": "v5.0.0-8.2.1",
      "level": 1,
      "chapter": "Authorization",
      "responsibility": "consumer",
      "status": "external",
      "evidence": "Consumer application control; outside the library boundary."
    },
    {
      "id": "v5.0.0-8.2.2",
      "level": 1,
      "chapter": "Authorization",
      "responsibility": "consumer",
      "status": "external",
      "evidence": "Consumer application control; outside the library boundary."
    },
    {
      "id": "v5.0.0-8.2.3",
      "level": 2,
      "chapter": "Authorization",
      "responsibility": "consumer",
      "status": "external",
      "evidence": "Consumer application control; outside the library boundary."
    },
    {
      "id": "v5.0.0-8.3.1",
      "level": 1,
      "chapter": "Authorization",
      "responsibility": "consumer",
      "status": "external",
      "evidence": "Consumer application control; outside the library boundary."
    },
    {
      "id": "v5.0.0-8.4.1",
      "level": 2,
      "chapter": "Authorization",
      "responsibility": "consumer",
      "status": "external",
      "evidence": "Consumer application control; outside the library boundary."
    },
    {
      "id": "v5.0.0-9.1.1",
      "level": 1,
      "chapter": "Self-contained Tokens",
      "responsibility": "upstream",
      "status": "external",
      "evidence": "Pinned Better Auth or Convex control; integration and provider verification required."
    },
    {
      "id": "v5.0.0-9.1.2",
      "level": 1,
      "chapter": "Self-contained Tokens",
      "responsibility": "upstream",
      "status": "external",
      "evidence": "Pinned Better Auth or Convex control; integration and provider verification required."
    },
    {
      "id": "v5.0.0-9.1.3",
      "level": 1,
      "chapter": "Self-contained Tokens",
      "responsibility": "upstream",
      "status": "external",
      "evidence": "Pinned Better Auth or Convex control; integration and provider verification required."
    },
    {
      "id": "v5.0.0-9.2.1",
      "level": 1,
      "chapter": "Self-contained Tokens",
      "responsibility": "upstream",
      "status": "external",
      "evidence": "Pinned Better Auth or Convex control; integration and provider verification required."
    },
    {
      "id": "v5.0.0-9.2.2",
      "level": 2,
      "chapter": "Self-contained Tokens",
      "responsibility": "upstream",
      "status": "external",
      "evidence": "Pinned Better Auth or Convex control; integration and provider verification required."
    },
    {
      "id": "v5.0.0-9.2.3",
      "level": 2,
      "chapter": "Self-contained Tokens",
      "responsibility": "upstream",
      "status": "external",
      "evidence": "Pinned Better Auth or Convex control; integration and provider verification required."
    },
    {
      "id": "v5.0.0-9.2.4",
      "level": 2,
      "chapter": "Self-contained Tokens",
      "responsibility": "upstream",
      "status": "external",
      "evidence": "Pinned Better Auth or Convex control; integration and provider verification required."
    },
    {
      "id": "v5.0.0-10.1.1",
      "level": 2,
      "chapter": "OAuth and OIDC",
      "responsibility": "library",
      "status": "verified",
      "evidence": "src/runtime/server/api/auth/headers.ts"
    },
    {
      "id": "v5.0.0-10.1.2",
      "level": 2,
      "chapter": "OAuth and OIDC",
      "responsibility": "upstream",
      "status": "external",
      "evidence": "Pinned Better Auth or Convex control; integration and provider verification required."
    },
    {
      "id": "v5.0.0-10.2.1",
      "level": 2,
      "chapter": "OAuth and OIDC",
      "responsibility": "upstream",
      "status": "external",
      "evidence": "Pinned Better Auth or Convex control; integration and provider verification required."
    },
    {
      "id": "v5.0.0-10.2.2",
      "level": 2,
      "chapter": "OAuth and OIDC",
      "responsibility": "upstream",
      "status": "external",
      "evidence": "Pinned Better Auth or Convex control; integration and provider verification required."
    },
    {
      "id": "v5.0.0-10.3.1",
      "level": 2,
      "chapter": "OAuth and OIDC",
      "responsibility": "upstream",
      "status": "external",
      "evidence": "Pinned Better Auth or Convex control; integration and provider verification required."
    },
    {
      "id": "v5.0.0-10.3.2",
      "level": 2,
      "chapter": "OAuth and OIDC",
      "responsibility": "upstream",
      "status": "external",
      "evidence": "Pinned Better Auth or Convex control; integration and provider verification required."
    },
    {
      "id": "v5.0.0-10.3.3",
      "level": 2,
      "chapter": "OAuth and OIDC",
      "responsibility": "upstream",
      "status": "external",
      "evidence": "Pinned Better Auth or Convex control; integration and provider verification required."
    },
    {
      "id": "v5.0.0-10.3.4",
      "level": 2,
      "chapter": "OAuth and OIDC",
      "responsibility": "upstream",
      "status": "external",
      "evidence": "Pinned Better Auth or Convex control; integration and provider verification required."
    },
    {
      "id": "v5.0.0-10.4.1",
      "level": 1,
      "chapter": "OAuth and OIDC",
      "responsibility": "upstream",
      "status": "external",
      "evidence": "Pinned Better Auth or Convex control; integration and provider verification required."
    },
    {
      "id": "v5.0.0-10.4.2",
      "level": 1,
      "chapter": "OAuth and OIDC",
      "responsibility": "upstream",
      "status": "external",
      "evidence": "Pinned Better Auth or Convex control; integration and provider verification required."
    },
    {
      "id": "v5.0.0-10.4.3",
      "level": 1,
      "chapter": "OAuth and OIDC",
      "responsibility": "upstream",
      "status": "external",
      "evidence": "Pinned Better Auth or Convex control; integration and provider verification required."
    },
    {
      "id": "v5.0.0-10.4.4",
      "level": 1,
      "chapter": "OAuth and OIDC",
      "responsibility": "upstream",
      "status": "external",
      "evidence": "Pinned Better Auth or Convex control; integration and provider verification required."
    },
    {
      "id": "v5.0.0-10.4.5",
      "level": 1,
      "chapter": "OAuth and OIDC",
      "responsibility": "upstream",
      "status": "external",
      "evidence": "Pinned Better Auth or Convex control; integration and provider verification required."
    },
    {
      "id": "v5.0.0-10.4.6",
      "level": 2,
      "chapter": "OAuth and OIDC",
      "responsibility": "upstream",
      "status": "external",
      "evidence": "Pinned Better Auth or Convex control; integration and provider verification required."
    },
    {
      "id": "v5.0.0-10.4.7",
      "level": 2,
      "chapter": "OAuth and OIDC",
      "responsibility": "upstream",
      "status": "external",
      "evidence": "Pinned Better Auth or Convex control; integration and provider verification required."
    },
    {
      "id": "v5.0.0-10.4.8",
      "level": 2,
      "chapter": "OAuth and OIDC",
      "responsibility": "upstream",
      "status": "external",
      "evidence": "Pinned Better Auth or Convex control; integration and provider verification required."
    },
    {
      "id": "v5.0.0-10.4.9",
      "level": 2,
      "chapter": "OAuth and OIDC",
      "responsibility": "upstream",
      "status": "external",
      "evidence": "Pinned Better Auth or Convex control; integration and provider verification required."
    },
    {
      "id": "v5.0.0-10.4.10",
      "level": 2,
      "chapter": "OAuth and OIDC",
      "responsibility": "upstream",
      "status": "external",
      "evidence": "Pinned Better Auth or Convex control; integration and provider verification required."
    },
    {
      "id": "v5.0.0-10.4.11",
      "level": 2,
      "chapter": "OAuth and OIDC",
      "responsibility": "upstream",
      "status": "external",
      "evidence": "Pinned Better Auth or Convex control; integration and provider verification required."
    },
    {
      "id": "v5.0.0-10.5.1",
      "level": 2,
      "chapter": "OAuth and OIDC",
      "responsibility": "upstream",
      "status": "external",
      "evidence": "Pinned Better Auth or Convex control; integration and provider verification required."
    },
    {
      "id": "v5.0.0-10.5.2",
      "level": 2,
      "chapter": "OAuth and OIDC",
      "responsibility": "upstream",
      "status": "external",
      "evidence": "Pinned Better Auth or Convex control; integration and provider verification required."
    },
    {
      "id": "v5.0.0-10.5.3",
      "level": 2,
      "chapter": "OAuth and OIDC",
      "responsibility": "upstream",
      "status": "external",
      "evidence": "Pinned Better Auth or Convex control; integration and provider verification required."
    },
    {
      "id": "v5.0.0-10.5.4",
      "level": 2,
      "chapter": "OAuth and OIDC",
      "responsibility": "upstream",
      "status": "external",
      "evidence": "Pinned Better Auth or Convex control; integration and provider verification required."
    },
    {
      "id": "v5.0.0-10.5.5",
      "level": 2,
      "chapter": "OAuth and OIDC",
      "responsibility": "upstream",
      "status": "external",
      "evidence": "Pinned Better Auth or Convex control; integration and provider verification required."
    },
    {
      "id": "v5.0.0-10.6.1",
      "level": 2,
      "chapter": "OAuth and OIDC",
      "responsibility": "upstream",
      "status": "external",
      "evidence": "Pinned Better Auth or Convex control; integration and provider verification required."
    },
    {
      "id": "v5.0.0-10.6.2",
      "level": 2,
      "chapter": "OAuth and OIDC",
      "responsibility": "upstream",
      "status": "external",
      "evidence": "Pinned Better Auth or Convex control; integration and provider verification required."
    },
    {
      "id": "v5.0.0-10.7.1",
      "level": 2,
      "chapter": "OAuth and OIDC",
      "responsibility": "upstream",
      "status": "external",
      "evidence": "Pinned Better Auth or Convex control; integration and provider verification required."
    },
    {
      "id": "v5.0.0-10.7.2",
      "level": 2,
      "chapter": "OAuth and OIDC",
      "responsibility": "upstream",
      "status": "external",
      "evidence": "Pinned Better Auth or Convex control; integration and provider verification required."
    },
    {
      "id": "v5.0.0-10.7.3",
      "level": 2,
      "chapter": "OAuth and OIDC",
      "responsibility": "upstream",
      "status": "external",
      "evidence": "Pinned Better Auth or Convex control; integration and provider verification required."
    },
    {
      "id": "v5.0.0-11.1.1",
      "level": 2,
      "chapter": "Cryptography",
      "responsibility": "upstream",
      "status": "external",
      "evidence": "Pinned Better Auth or Convex control; integration and provider verification required."
    },
    {
      "id": "v5.0.0-11.1.2",
      "level": 2,
      "chapter": "Cryptography",
      "responsibility": "upstream",
      "status": "external",
      "evidence": "Pinned Better Auth or Convex control; integration and provider verification required."
    },
    {
      "id": "v5.0.0-11.2.1",
      "level": 2,
      "chapter": "Cryptography",
      "responsibility": "upstream",
      "status": "external",
      "evidence": "Pinned Better Auth or Convex control; integration and provider verification required."
    },
    {
      "id": "v5.0.0-11.2.2",
      "level": 2,
      "chapter": "Cryptography",
      "responsibility": "upstream",
      "status": "external",
      "evidence": "Pinned Better Auth or Convex control; integration and provider verification required."
    },
    {
      "id": "v5.0.0-11.2.3",
      "level": 2,
      "chapter": "Cryptography",
      "responsibility": "upstream",
      "status": "external",
      "evidence": "Pinned Better Auth or Convex control; integration and provider verification required."
    },
    {
      "id": "v5.0.0-11.3.1",
      "level": 1,
      "chapter": "Cryptography",
      "responsibility": "upstream",
      "status": "external",
      "evidence": "Pinned Better Auth or Convex control; integration and provider verification required."
    },
    {
      "id": "v5.0.0-11.3.2",
      "level": 1,
      "chapter": "Cryptography",
      "responsibility": "upstream",
      "status": "external",
      "evidence": "Pinned Better Auth or Convex control; integration and provider verification required."
    },
    {
      "id": "v5.0.0-11.3.3",
      "level": 2,
      "chapter": "Cryptography",
      "responsibility": "upstream",
      "status": "external",
      "evidence": "Pinned Better Auth or Convex control; integration and provider verification required."
    },
    {
      "id": "v5.0.0-11.4.1",
      "level": 1,
      "chapter": "Cryptography",
      "responsibility": "upstream",
      "status": "external",
      "evidence": "Pinned Better Auth or Convex control; integration and provider verification required."
    },
    {
      "id": "v5.0.0-11.4.2",
      "level": 2,
      "chapter": "Cryptography",
      "responsibility": "upstream",
      "status": "external",
      "evidence": "Pinned Better Auth or Convex control; integration and provider verification required."
    },
    {
      "id": "v5.0.0-11.4.3",
      "level": 2,
      "chapter": "Cryptography",
      "responsibility": "upstream",
      "status": "external",
      "evidence": "Pinned Better Auth or Convex control; integration and provider verification required."
    },
    {
      "id": "v5.0.0-11.4.4",
      "level": 2,
      "chapter": "Cryptography",
      "responsibility": "upstream",
      "status": "external",
      "evidence": "Pinned Better Auth or Convex control; integration and provider verification required."
    },
    {
      "id": "v5.0.0-11.5.1",
      "level": 2,
      "chapter": "Cryptography",
      "responsibility": "upstream",
      "status": "external",
      "evidence": "Pinned Better Auth or Convex control; integration and provider verification required."
    },
    {
      "id": "v5.0.0-11.6.1",
      "level": 2,
      "chapter": "Cryptography",
      "responsibility": "upstream",
      "status": "external",
      "evidence": "Pinned Better Auth or Convex control; integration and provider verification required."
    },
    {
      "id": "v5.0.0-12.1.1",
      "level": 1,
      "chapter": "Secure Communication",
      "responsibility": "deployment",
      "status": "external",
      "evidence": "Deployment control; operator verification required."
    },
    {
      "id": "v5.0.0-12.1.2",
      "level": 2,
      "chapter": "Secure Communication",
      "responsibility": "deployment",
      "status": "external",
      "evidence": "Deployment control; operator verification required."
    },
    {
      "id": "v5.0.0-12.1.3",
      "level": 2,
      "chapter": "Secure Communication",
      "responsibility": "deployment",
      "status": "external",
      "evidence": "Deployment control; operator verification required."
    },
    {
      "id": "v5.0.0-12.2.1",
      "level": 1,
      "chapter": "Secure Communication",
      "responsibility": "library",
      "status": "verified",
      "evidence": "src/runtime/utils/site-url.ts"
    },
    {
      "id": "v5.0.0-12.2.2",
      "level": 1,
      "chapter": "Secure Communication",
      "responsibility": "deployment",
      "status": "external",
      "evidence": "Deployment control; operator verification required."
    },
    {
      "id": "v5.0.0-12.3.1",
      "level": 2,
      "chapter": "Secure Communication",
      "responsibility": "library",
      "status": "verified",
      "evidence": "src/runtime/utils/site-url.ts"
    },
    {
      "id": "v5.0.0-12.3.2",
      "level": 2,
      "chapter": "Secure Communication",
      "responsibility": "deployment",
      "status": "external",
      "evidence": "Deployment control; operator verification required."
    },
    {
      "id": "v5.0.0-12.3.3",
      "level": 2,
      "chapter": "Secure Communication",
      "responsibility": "deployment",
      "status": "external",
      "evidence": "Deployment control; operator verification required."
    },
    {
      "id": "v5.0.0-12.3.4",
      "level": 2,
      "chapter": "Secure Communication",
      "responsibility": "deployment",
      "status": "external",
      "evidence": "Deployment control; operator verification required."
    },
    {
      "id": "v5.0.0-13.1.1",
      "level": 2,
      "chapter": "Configuration",
      "responsibility": "library",
      "status": "verified",
      "evidence": "src/ARCHITECTURE.md"
    },
    {
      "id": "v5.0.0-13.2.1",
      "level": 2,
      "chapter": "Configuration",
      "responsibility": "deployment",
      "status": "external",
      "evidence": "Deployment control; operator verification required."
    },
    {
      "id": "v5.0.0-13.2.2",
      "level": 2,
      "chapter": "Configuration",
      "responsibility": "deployment",
      "status": "external",
      "evidence": "Deployment control; operator verification required."
    },
    {
      "id": "v5.0.0-13.2.3",
      "level": 2,
      "chapter": "Configuration",
      "responsibility": "deployment",
      "status": "external",
      "evidence": "Deployment control; operator verification required."
    },
    {
      "id": "v5.0.0-13.2.4",
      "level": 2,
      "chapter": "Configuration",
      "responsibility": "library",
      "status": "verified",
      "evidence": "src/runtime/utils/site-url.ts"
    },
    {
      "id": "v5.0.0-13.2.5",
      "level": 2,
      "chapter": "Configuration",
      "responsibility": "library",
      "status": "verified",
      "evidence": "src/runtime/utils/site-url.ts"
    },
    {
      "id": "v5.0.0-13.3.1",
      "level": 2,
      "chapter": "Configuration",
      "responsibility": "deployment",
      "status": "external",
      "evidence": "Deployment control; operator verification required."
    },
    {
      "id": "v5.0.0-13.3.2",
      "level": 2,
      "chapter": "Configuration",
      "responsibility": "deployment",
      "status": "external",
      "evidence": "Deployment control; operator verification required."
    },
    {
      "id": "v5.0.0-13.4.1",
      "level": 1,
      "chapter": "Configuration",
      "responsibility": "deployment",
      "status": "external",
      "evidence": "Deployment control; operator verification required."
    },
    {
      "id": "v5.0.0-13.4.2",
      "level": 2,
      "chapter": "Configuration",
      "responsibility": "library",
      "status": "verified",
      "evidence": "test/security/proxy-regressions.test.ts"
    },
    {
      "id": "v5.0.0-13.4.3",
      "level": 2,
      "chapter": "Configuration",
      "responsibility": "deployment",
      "status": "external",
      "evidence": "Deployment control; operator verification required."
    },
    {
      "id": "v5.0.0-13.4.4",
      "level": 2,
      "chapter": "Configuration",
      "responsibility": "library",
      "status": "verified",
      "evidence": "src/runtime/server/api/auth/[...].ts"
    },
    {
      "id": "v5.0.0-13.4.5",
      "level": 2,
      "chapter": "Configuration",
      "responsibility": "deployment",
      "status": "external",
      "evidence": "Deployment control; operator verification required."
    },
    {
      "id": "v5.0.0-14.1.1",
      "level": 2,
      "chapter": "Data Protection",
      "responsibility": "consumer",
      "status": "external",
      "evidence": "Consumer application control; outside the library boundary."
    },
    {
      "id": "v5.0.0-14.1.2",
      "level": 2,
      "chapter": "Data Protection",
      "responsibility": "consumer",
      "status": "external",
      "evidence": "Consumer application control; outside the library boundary."
    },
    {
      "id": "v5.0.0-14.2.1",
      "level": 1,
      "chapter": "Data Protection",
      "responsibility": "consumer",
      "status": "external",
      "evidence": "Consumer application control; outside the library boundary."
    },
    {
      "id": "v5.0.0-14.2.2",
      "level": 2,
      "chapter": "Data Protection",
      "responsibility": "library",
      "status": "verified",
      "evidence": "src/runtime/server/api/auth/[...].ts"
    },
    {
      "id": "v5.0.0-14.2.3",
      "level": 2,
      "chapter": "Data Protection",
      "responsibility": "consumer",
      "status": "external",
      "evidence": "Consumer application control; outside the library boundary."
    },
    {
      "id": "v5.0.0-14.2.4",
      "level": 2,
      "chapter": "Data Protection",
      "responsibility": "consumer",
      "status": "external",
      "evidence": "Consumer application control; outside the library boundary."
    },
    {
      "id": "v5.0.0-14.3.1",
      "level": 1,
      "chapter": "Data Protection",
      "responsibility": "library",
      "status": "verified",
      "evidence": "internal/evidence/asvs-client-lifecycle-cutover-2026-07-22.md"
    },
    {
      "id": "v5.0.0-14.3.2",
      "level": 2,
      "chapter": "Data Protection",
      "responsibility": "library",
      "status": "verified",
      "evidence": "test/security/proxy-regressions.test.ts"
    },
    {
      "id": "v5.0.0-14.3.3",
      "level": 2,
      "chapter": "Data Protection",
      "responsibility": "consumer",
      "status": "external",
      "evidence": "Consumer application control; outside the library boundary."
    },
    {
      "id": "v5.0.0-15.1.1",
      "level": 1,
      "chapter": "Secure Coding and Architecture",
      "responsibility": "library",
      "status": "verified",
      "evidence": "SECURITY.md"
    },
    {
      "id": "v5.0.0-15.1.2",
      "level": 2,
      "chapter": "Secure Coding and Architecture",
      "responsibility": "library",
      "status": "verified",
      "evidence": "scripts/generate-sbom.mjs"
    },
    {
      "id": "v5.0.0-15.1.3",
      "level": 2,
      "chapter": "Secure Coding and Architecture",
      "responsibility": "library",
      "status": "verified",
      "evidence": "src/ARCHITECTURE.md"
    },
    {
      "id": "v5.0.0-15.2.1",
      "level": 1,
      "chapter": "Secure Coding and Architecture",
      "responsibility": "library",
      "status": "verified",
      "evidence": ".github/workflows/ci.yml"
    },
    {
      "id": "v5.0.0-15.2.2",
      "level": 2,
      "chapter": "Secure Coding and Architecture",
      "responsibility": "library",
      "status": "verified",
      "evidence": "src/runtime/server/api/auth/body-size.ts"
    },
    {
      "id": "v5.0.0-15.2.3",
      "level": 2,
      "chapter": "Secure Coding and Architecture",
      "responsibility": "library",
      "status": "verified",
      "evidence": "scripts/check-package-exports.mjs"
    },
    {
      "id": "v5.0.0-15.3.1",
      "level": 1,
      "chapter": "Secure Coding and Architecture",
      "responsibility": "consumer",
      "status": "external",
      "evidence": "Consumer application control; outside the library boundary."
    },
    {
      "id": "v5.0.0-15.3.2",
      "level": 2,
      "chapter": "Secure Coding and Architecture",
      "responsibility": "library",
      "status": "verified",
      "evidence": "test/security/proxy-regressions.test.ts"
    },
    {
      "id": "v5.0.0-15.3.3",
      "level": 2,
      "chapter": "Secure Coding and Architecture",
      "responsibility": "consumer",
      "status": "external",
      "evidence": "Consumer application control; outside the library boundary."
    },
    {
      "id": "v5.0.0-15.3.4",
      "level": 2,
      "chapter": "Secure Coding and Architecture",
      "responsibility": "library",
      "status": "verified",
      "evidence": "test/unit/auth-proxy-headers.test.ts"
    },
    {
      "id": "v5.0.0-15.3.5",
      "level": 2,
      "chapter": "Secure Coding and Architecture",
      "responsibility": "library",
      "status": "verified",
      "evidence": "tsconfig.json"
    },
    {
      "id": "v5.0.0-15.3.6",
      "level": 2,
      "chapter": "Secure Coding and Architecture",
      "responsibility": "consumer",
      "status": "external",
      "evidence": "Consumer application control; outside the library boundary."
    },
    {
      "id": "v5.0.0-15.3.7",
      "level": 2,
      "chapter": "Secure Coding and Architecture",
      "responsibility": "consumer",
      "status": "external",
      "evidence": "Consumer application control; outside the library boundary."
    },
    {
      "id": "v5.0.0-16.1.1",
      "level": 2,
      "chapter": "Security Logging and Error Handling",
      "responsibility": "deployment",
      "status": "external",
      "evidence": "Deployment control; operator verification required."
    },
    {
      "id": "v5.0.0-16.2.1",
      "level": 2,
      "chapter": "Security Logging and Error Handling",
      "responsibility": "deployment",
      "status": "external",
      "evidence": "Deployment control; operator verification required."
    },
    {
      "id": "v5.0.0-16.2.2",
      "level": 2,
      "chapter": "Security Logging and Error Handling",
      "responsibility": "deployment",
      "status": "external",
      "evidence": "Deployment control; operator verification required."
    },
    {
      "id": "v5.0.0-16.2.3",
      "level": 2,
      "chapter": "Security Logging and Error Handling",
      "responsibility": "deployment",
      "status": "external",
      "evidence": "Deployment control; operator verification required."
    },
    {
      "id": "v5.0.0-16.2.4",
      "level": 2,
      "chapter": "Security Logging and Error Handling",
      "responsibility": "deployment",
      "status": "external",
      "evidence": "Deployment control; operator verification required."
    },
    {
      "id": "v5.0.0-16.2.5",
      "level": 2,
      "chapter": "Security Logging and Error Handling",
      "responsibility": "library",
      "status": "verified",
      "evidence": "src/runtime/utils/sanitize-diagnostic.ts"
    },
    {
      "id": "v5.0.0-16.3.1",
      "level": 2,
      "chapter": "Security Logging and Error Handling",
      "responsibility": "deployment",
      "status": "external",
      "evidence": "Deployment control; operator verification required."
    },
    {
      "id": "v5.0.0-16.3.2",
      "level": 2,
      "chapter": "Security Logging and Error Handling",
      "responsibility": "deployment",
      "status": "external",
      "evidence": "Deployment control; operator verification required."
    },
    {
      "id": "v5.0.0-16.3.3",
      "level": 2,
      "chapter": "Security Logging and Error Handling",
      "responsibility": "deployment",
      "status": "external",
      "evidence": "Deployment control; operator verification required."
    },
    {
      "id": "v5.0.0-16.3.4",
      "level": 2,
      "chapter": "Security Logging and Error Handling",
      "responsibility": "deployment",
      "status": "external",
      "evidence": "Deployment control; operator verification required."
    },
    {
      "id": "v5.0.0-16.4.1",
      "level": 2,
      "chapter": "Security Logging and Error Handling",
      "responsibility": "library",
      "status": "verified",
      "evidence": "src/runtime/utils/sanitize-diagnostic.ts"
    },
    {
      "id": "v5.0.0-16.4.2",
      "level": 2,
      "chapter": "Security Logging and Error Handling",
      "responsibility": "deployment",
      "status": "external",
      "evidence": "Deployment control; operator verification required."
    },
    {
      "id": "v5.0.0-16.4.3",
      "level": 2,
      "chapter": "Security Logging and Error Handling",
      "responsibility": "deployment",
      "status": "external",
      "evidence": "Deployment control; operator verification required."
    },
    {
      "id": "v5.0.0-16.5.1",
      "level": 2,
      "chapter": "Security Logging and Error Handling",
      "responsibility": "library",
      "status": "verified",
      "evidence": "test/security/proxy-regressions.test.ts"
    },
    {
      "id": "v5.0.0-16.5.2",
      "level": 2,
      "chapter": "Security Logging and Error Handling",
      "responsibility": "library",
      "status": "verified",
      "evidence": "internal/evidence/asvs-client-lifecycle-cutover-2026-07-22.md"
    },
    {
      "id": "v5.0.0-16.5.3",
      "level": 2,
      "chapter": "Security Logging and Error Handling",
      "responsibility": "library",
      "status": "verified",
      "evidence": "internal/evidence/asvs-client-lifecycle-cutover-2026-07-22.md"
    },
    {
      "id": "v5.0.0-17.1.1",
      "level": 2,
      "chapter": "WebRTC",
      "responsibility": "not-applicable",
      "status": "external",
      "evidence": "The library does not implement WebRTC."
    },
    {
      "id": "v5.0.0-17.2.1",
      "level": 2,
      "chapter": "WebRTC",
      "responsibility": "not-applicable",
      "status": "external",
      "evidence": "The library does not implement WebRTC."
    },
    {
      "id": "v5.0.0-17.2.2",
      "level": 2,
      "chapter": "WebRTC",
      "responsibility": "not-applicable",
      "status": "external",
      "evidence": "The library does not implement WebRTC."
    },
    {
      "id": "v5.0.0-17.2.3",
      "level": 2,
      "chapter": "WebRTC",
      "responsibility": "not-applicable",
      "status": "external",
      "evidence": "The library does not implement WebRTC."
    },
    {
      "id": "v5.0.0-17.2.4",
      "level": 2,
      "chapter": "WebRTC",
      "responsibility": "not-applicable",
      "status": "external",
      "evidence": "The library does not implement WebRTC."
    },
    {
      "id": "v5.0.0-17.3.1",
      "level": 2,
      "chapter": "WebRTC",
      "responsibility": "not-applicable",
      "status": "external",
      "evidence": "The library does not implement WebRTC."
    },
    {
      "id": "v5.0.0-17.3.2",
      "level": 2,
      "chapter": "WebRTC",
      "responsibility": "not-applicable",
      "status": "external",
      "evidence": "The library does not implement WebRTC."
    }
  ]
}
